mealprep/__init__.py
mealprep/mealprep.py
mealprep-1.0.15.dist-info/LICENSE
mealprep-1.0.15.dist-info/WHEEL
mealprep-1.0.15.dist-info/METADATA
mealprep-1.0.15.dist-info/RECORD
