Metadata-Version: 2.1
Name: mealprep
Version: 1.0.15
Summary: Python package that ease the pain in pre-processing like outlier finding, numerical/categorical data and etc.
Home-page: https://github.com/UBC-MDS/mealprep
License: MIT
Author: luhuayue
Author-email: luhuayueapp@163.com
Requires-Python: >=3.6.1,<4.0.0
Classifier: License :: OSI Approved :: MIT License
Classifier: Programming Language :: Python :: 3
Classifier: Programming Language :: Python :: 3.7
Classifier: Programming Language :: Python :: 3.8
Requires-Dist: codecov (>=2.0.16,<3.0.0)
Requires-Dist: flake8 (>=3.7.9,<4.0.0)
Requires-Dist: pandas (>=1.0.1,<2.0.0)
Requires-Dist: python-semantic-release (>=4.10.0,<5.0.0)
Requires-Dist: sklearn (>=0.0,<0.1)
Requires-Dist: sphinxcontrib-napoleon (>=0.7,<0.8)
Requires-Dist: vega_datasets (>=0.8.0,<0.9.0)
Project-URL: Documentation, https://mealprep.readthedocs.io
Project-URL: Repository, https://github.com/UBC-MDS/mealprep
